neuralpuzzle/__init__.py
neuralpuzzle/cli.py
neuralpuzzle/gen_cnn.py
neuralpuzzle/gen_network.py
neuralpuzzle/initializer.py
neuralpuzzle/layers.py
neuralpuzzle/neuralpuzzle.py
neuralpuzzle/ops.py
neuralpuzzle/optimizer.py
neuralpuzzle/rnd.py
neuralpuzzle/train_network.py
neuralpuzzle/utils.py
neuralpuzzle-0.1.0a1.dist-info/DESCRIPTION.rst
neuralpuzzle-0.1.0a1.dist-info/METADATA
neuralpuzzle-0.1.0a1.dist-info/RECORD
neuralpuzzle-0.1.0a1.dist-info/WHEEL
neuralpuzzle-0.1.0a1.dist-info/entry_points.txt
neuralpuzzle-0.1.0a1.dist-info/metadata.json
neuralpuzzle-0.1.0a1.dist-info/top_level.txt
