Metadata-Version: 2.0
Name: neuralpuzzle
Version: 0.1.0a1
Summary: A Simple Python package that helps anyone
Home-page: https://github.com/cxmaro-s/neuralpuzzle
Author: Runze Sun
Author-email: fihyer@me.com
License: GNU General Public License v3
Keywords: neuralpuzzle
Platform: UNKNOWN
Classifier: Development Status :: 2 - Pre-Alpha
Classifier: Intended Audience :: Developers
Classifier: License :: OSI Approved :: GNU General Public License v3 (GPLv3)
Classifier: Natural Language :: English
Classifier: Programming Language :: Python :: 2
Classifier: Programming Language :: Python :: 2.6
Classifier: Programming Language :: Python :: 2.7
Classifier: Programming Language :: Python :: 3
Classifier: Programming Language :: Python :: 3.3
Classifier: Programming Language :: Python :: 3.4
Classifier: Programming Language :: Python :: 3.5
Requires-Dist: Click (>=6.0)
Requires-Dist: numpy
